channels_handlers/__init__.py
channels_handlers/consumers.py
channels_handlers/handlers.py
django_channels_handlers-0.2.2.dist-info/LICENSE
django_channels_handlers-0.2.2.dist-info/WHEEL
django_channels_handlers-0.2.2.dist-info/METADATA
django_channels_handlers-0.2.2.dist-info/RECORD
