Metadata-Version: 2.1
Name: django-channels-handlers
Version: 0.2.2
Summary: Django Channels, without the Pain
Home-page: https://github.com/joshua-s/django-channels-handlers
License: MIT
Author: Josh Smith
Author-email: josh@joshsmith.codes
Requires-Python: >=3.7
Classifier: Development Status :: 3 - Alpha
Classifier: Framework :: Django
Classifier: Framework :: Django :: 2.2
Classifier: Framework :: Django :: 3.0
Classifier: Intended Audience :: Developers
Classifier: License :: OSI Approved :: MIT License
Classifier: Programming Language :: Python :: 3
Classifier: Programming Language :: Python :: 3.7
Classifier: Programming Language :: Python :: 3.8
Project-URL: Repository, https://github.com/joshua-s/django-channels-handlers
